{"title":"Créez ! Editez ! Modifiez ! Facilement..","subtitle":"Sortez votre plus belle plume pour susciter l'envie de votre visiteur par le biais d'une description courte qui lui donnera envie d'en savoir plus !","logo":"Lyatom-CMS.gif","infoSection":[{"title":"Simple à prendre en main","subtitle":"Grace à sa barre latérale, consultez en direct le contenu modifié","logo":"feature-01-light.png"},{"title":"Rapide","subtitle":"Sauvegardez...et quelques minutes après...c'est tout ! C'est en ligne 😉","logo":"feature-02-light.png"},{"title":"Efficace","subtitle":"Utile pour les sites vitrines, Landing Pages, pages produits ou bien d'autres, Lyatom CMS vous simplifie la vie 🤓","logo":"feature-03-light.png"}]}